biomap/__init__.py
biomap/backend/__init__.py
biomap/backend/mongodb/__init__.py
biomap/backend/mongodb/database.py
biomap/backend/mongodb/mapper.py
biomap_mongodb-0.0.49.dist-info/LICENSE
biomap_mongodb-0.0.49.dist-info/METADATA
biomap_mongodb-0.0.49.dist-info/WHEEL
biomap_mongodb-0.0.49.dist-info/top_level.txt
biomap_mongodb-0.0.49.dist-info/RECORD
